[
    {
        "block_id": 328280, 
        "direction_id": 1, 
        "hierarchy": 1, 
        "pattern_rank": 2, 
        "pattern_id": 100, 
        "route_id": "88-PrinceGeorge", 
        "direction_code": 0, 
        "trip_headsign": "Westgate Mall", 
        "trip_type": 0, 
        "trip_sequence": 2, 
        "shape_id": "9-88-14", 
        "pattern_code": 100, 
        "service_id": "aaJUN16-JUN16-Weekday-03", 
        "trip_id": "ab1893586", 
        "pattern_count": 1633
    }, 
    {
        "block_id": 328280, 
        "direction_id": 1, 
        "hierarchy": 1, 
        "pattern_rank": 2, 
        "pattern_id": 100, 
        "route_id": "88-PrinceGeorge", 
        "direction_code": 0, 
        "trip_headsign": "Westgate Mall", 
        "trip_type": 0, 
        "trip_sequence": 4, 
        "shape_id": "9-88-14", 
        "pattern_code": 100, 
        "service_id": "aaJUN16-JUN16-Weekday-03", 
        "trip_id": "ab1893588", 
        "pattern_count": 1633
    }, 
    {
        "block_id": 328280, 
        "direction_id": 1, 
        "hierarchy": 1, 
        "pattern_rank": 2, 
        "pattern_id": 100, 
        "route_id": "88-PrinceGeorge", 
        "direction_code": 0, 
        "trip_headsign": "Westgate Mall", 
        "trip_type": 0, 
        "trip_sequence": 6, 
        "shape_id": "9-88-14", 
        "pattern_code": 100, 
        "service_id": "aaJUN16-JUN16-Weekday-03", 
        "trip_id": "ab1893590", 
        "pattern_count": 1633
    }, 
    {
        "block_id": 328280, 
        "direction_id": 1, 
        "hierarchy": 1, 
        "pattern_rank": 2, 
        "pattern_id": 100, 
        "route_id": "88-PrinceGeorge", 
        "direction_code": 0, 
        "trip_headsign": "Westgate Mall", 
        "trip_type": 0, 
        "trip_sequence": 8, 
        "shape_id": "9-88-14", 
        "pattern_code": 100, 
        "service_id": "aaJUN16-JUN16-Weekday-03", 
        "trip_id": "ab1893592", 
        "pattern_count": 1633
    }, 
    {
        "block_id": 328280, 
        "direction_id": 1, 
        "hierarchy": 1, 
        "pattern_rank": 2, 
        "pattern_id": 100, 
        "route_id": "88-PrinceGeorge", 
        "direction_code": 0, 
        "trip_headsign": "Westgate Mall", 
        "trip_type": 0, 
        "trip_sequence": 10, 
        "shape_id": "9-88-14", 
        "pattern_code": 100, 
        "service_id": "aaJUN16-JUN16-Weekday-03", 
        "trip_id": "ab1893594", 
        "pattern_count": 1633
    }, 
    {
        "block_id": 328280, 
        "direction_id": 1, 
        "hierarchy": 1, 
        "pattern_rank": 2, 
        "pattern_id": 100, 
        "route_id": "88-PrinceGeorge", 
        "direction_code": 0, 
        "trip_headsign": "Westgate Mall", 
        "trip_type": 0, 
        "trip_sequence": 12, 
        "shape_id": "9-88-14", 
        "pattern_code": 100, 
        "service_id": "aaJUN16-JUN16-Weekday-03", 
        "trip_id": "ab1893596", 
        "pattern_count": 1633
    }, 
    {
        "block_id": 328281, 
        "direction_id": 1, 
        "hierarchy": 1, 
        "pattern_rank": 2, 
        "pattern_id": 100, 
        "route_id": "88-PrinceGeorge", 
        "direction_code": 0, 
        "trip_headsign": "Westgate Mall", 
        "trip_type": 0, 
        "trip_sequence": 2, 
        "shape_id": "9-88-14", 
        "pattern_code": 100, 
        "service_id": "aaJUN16-JUN16-Weekday-03", 
        "trip_id": "ab1893569", 
        "pattern_count": 1633
    }, 
    {
        "block_id": 328281, 
        "direction_id": 1, 
        "hierarchy": 1, 
        "pattern_rank": 2, 
        "pattern_id": 100, 
        "route_id": "88-PrinceGeorge", 
        "direction_code": 0, 
        "trip_headsign": "Westgate Mall", 
        "trip_type": 0, 
        "trip_sequence": 4, 
        "shape_id": "9-88-14", 
        "pattern_code": 100, 
        "service_id": "aaJUN16-JUN16-Weekday-03", 
        "trip_id": "ab1893571", 
        "pattern_count": 1633
    }, 
    {
        "block_id": 328281, 
        "direction_id": 1, 
        "hierarchy": 1, 
        "pattern_rank": 2, 
        "pattern_id": 100, 
        "route_id": "88-PrinceGeorge", 
        "direction_code": 0, 
        "trip_headsign": "Westgate Mall", 
        "trip_type": 0, 
        "trip_sequence": 6, 
        "shape_id": "9-88-14", 
        "pattern_code": 100, 
        "service_id": "aaJUN16-JUN16-Weekday-03", 
        "trip_id": "ab1893573", 
        "pattern_count": 1633
    }, 
    {
        "block_id": 328281, 
        "direction_id": 1, 
        "hierarchy": 1, 
        "pattern_rank": 2, 
        "pattern_id": 100, 
        "route_id": "88-PrinceGeorge", 
        "direction_code": 0, 
        "trip_headsign": "Westgate Mall", 
        "trip_type": 0, 
        "trip_sequence": 8, 
        "shape_id": "9-88-14", 
        "pattern_code": 100, 
        "service_id": "aaJUN16-JUN16-Weekday-03", 
        "trip_id": "ab1893575", 
        "pattern_count": 1633
    }, 
    {
        "block_id": 328281, 
        "direction_id": 1, 
        "hierarchy": 1, 
        "pattern_rank": 2, 
        "pattern_id": 100, 
        "route_id": "88-PrinceGeorge", 
        "direction_code": 0, 
        "trip_headsign": "Westgate Mall", 
        "trip_type": 0, 
        "trip_sequence": 10, 
        "shape_id": "9-88-14", 
        "pattern_code": 100, 
        "service_id": "aaJUN16-JUN16-Weekday-03", 
        "trip_id": "ab1893577", 
        "pattern_count": 1633
    }, 
    {
        "block_id": 328281, 
        "direction_id": 1, 
        "hierarchy": 1, 
        "pattern_rank": 2, 
        "pattern_id": 100, 
        "route_id": "88-PrinceGeorge", 
        "direction_code": 0, 
        "trip_headsign": "Westgate Mall", 
        "trip_type": 0, 
        "trip_sequence": 12, 
        "shape_id": "9-88-14", 
        "pattern_code": 100, 
        "service_id": "aaJUN16-JUN16-Weekday-03", 
        "trip_id": "ab1893579", 
        "pattern_count": 1633
    }, 
    {
        "block_id": 328281, 
        "direction_id": 1, 
        "hierarchy": 1, 
        "pattern_rank": 2, 
        "pattern_id": 100, 
        "route_id": "88-PrinceGeorge", 
        "direction_code": 0, 
        "trip_headsign": "Westgate Mall", 
        "trip_type": 0, 
        "trip_sequence": 14, 
        "shape_id": "9-88-14", 
        "pattern_code": 100, 
        "service_id": "aaJUN16-JUN16-Weekday-03", 
        "trip_id": "ab1893581", 
        "pattern_count": 1633
    }, 
    {
        "block_id": 328281, 
        "direction_id": 1, 
        "hierarchy": 1, 
        "pattern_rank": 2, 
        "pattern_id": 100, 
        "route_id": "88-PrinceGeorge", 
        "direction_code": 0, 
        "trip_headsign": "Westgate Mall", 
        "trip_type": 0, 
        "trip_sequence": 16, 
        "shape_id": "9-88-14", 
        "pattern_code": 100, 
        "service_id": "aaJUN16-JUN16-Weekday-03", 
        "trip_id": "ab1893583", 
        "pattern_count": 1633
    }, 
    {
        "block_id": 328299, 
        "direction_id": 1, 
        "hierarchy": 1, 
        "pattern_rank": 2, 
        "pattern_id": 100, 
        "route_id": "88-PrinceGeorge", 
        "direction_code": 0, 
        "trip_headsign": "Westgate Mall", 
        "trip_type": 0, 
        "trip_sequence": 2, 
        "shape_id": "9-88-14", 
        "pattern_code": 100, 
        "service_id": "aaJUN16-JUN16-Weekday-03", 
        "trip_id": "ab1893585", 
        "pattern_count": 1633
    }, 
    {
        "block_id": 328299, 
        "direction_id": 1, 
        "hierarchy": 1, 
        "pattern_rank": 2, 
        "pattern_id": 100, 
        "route_id": "88-PrinceGeorge", 
        "direction_code": 0, 
        "trip_headsign": "Westgate Mall", 
        "trip_type": 0, 
        "trip_sequence": 4, 
        "shape_id": "9-88-14", 
        "pattern_code": 100, 
        "service_id": "aaJUN16-JUN16-Weekday-03", 
        "trip_id": "ab1893587", 
        "pattern_count": 1633
    }, 
    {
        "block_id": 328299, 
        "direction_id": 1, 
        "hierarchy": 1, 
        "pattern_rank": 2, 
        "pattern_id": 100, 
        "route_id": "88-PrinceGeorge", 
        "direction_code": 0, 
        "trip_headsign": "Westgate Mall", 
        "trip_type": 0, 
        "trip_sequence": 6, 
        "shape_id": "9-88-14", 
        "pattern_code": 100, 
        "service_id": "aaJUN16-JUN16-Weekday-03", 
        "trip_id": "ab1893589", 
        "pattern_count": 1633
    }, 
    {
        "block_id": 328299, 
        "direction_id": 1, 
        "hierarchy": 1, 
        "pattern_rank": 2, 
        "pattern_id": 100, 
        "route_id": "88-PrinceGeorge", 
        "direction_code": 0, 
        "trip_headsign": "Westgate Mall", 
        "trip_type": 0, 
        "trip_sequence": 8, 
        "shape_id": "9-88-14", 
        "pattern_code": 100, 
        "service_id": "aaJUN16-JUN16-Weekday-03", 
        "trip_id": "ab1893591", 
        "pattern_count": 1633
    }, 
    {
        "block_id": 328299, 
        "direction_id": 1, 
        "hierarchy": 1, 
        "pattern_rank": 2, 
        "pattern_id": 100, 
        "route_id": "88-PrinceGeorge", 
        "direction_code": 0, 
        "trip_headsign": "Westgate Mall", 
        "trip_type": 0, 
        "trip_sequence": 10, 
        "shape_id": "9-88-14", 
        "pattern_code": 100, 
        "service_id": "aaJUN16-JUN16-Weekday-03", 
        "trip_id": "ab1893593", 
        "pattern_count": 1633
    }, 
    {
        "block_id": 328299, 
        "direction_id": 1, 
        "hierarchy": 1, 
        "pattern_rank": 2, 
        "pattern_id": 100, 
        "route_id": "88-PrinceGeorge", 
        "direction_code": 0, 
        "trip_headsign": "Westgate Mall", 
        "trip_type": 0, 
        "trip_sequence": 12, 
        "shape_id": "9-88-14", 
        "pattern_code": 100, 
        "service_id": "aaJUN16-JUN16-Weekday-03", 
        "trip_id": "ab1893595", 
        "pattern_count": 1633
    }, 
    {
        "block_id": 328299, 
        "direction_id": 1, 
        "hierarchy": 1, 
        "pattern_rank": 2, 
        "pattern_id": 100, 
        "route_id": "88-PrinceGeorge", 
        "direction_code": 0, 
        "trip_headsign": "Westgate Mall", 
        "trip_type": 0, 
        "trip_sequence": 14, 
        "shape_id": "9-88-14", 
        "pattern_code": 100, 
        "service_id": "aaJUN16-JUN16-Weekday-03", 
        "trip_id": "ab1893597", 
        "pattern_count": 1633
    }, 
    {
        "block_id": 328300, 
        "direction_id": 1, 
        "hierarchy": 1, 
        "pattern_rank": 2, 
        "pattern_id": 100, 
        "route_id": "88-PrinceGeorge", 
        "direction_code": 0, 
        "trip_headsign": "Westgate Mall", 
        "trip_type": 0, 
        "trip_sequence": 2, 
        "shape_id": "9-88-14", 
        "pattern_code": 100, 
        "service_id": "aaJUN16-JUN16-Weekday-03", 
        "trip_id": "ab1893568", 
        "pattern_count": 1633
    }, 
    {
        "block_id": 328300, 
        "direction_id": 1, 
        "hierarchy": 1, 
        "pattern_rank": 2, 
        "pattern_id": 100, 
        "route_id": "88-PrinceGeorge", 
        "direction_code": 0, 
        "trip_headsign": "Westgate Mall", 
        "trip_type": 0, 
        "trip_sequence": 4, 
        "shape_id": "9-88-14", 
        "pattern_code": 100, 
        "service_id": "aaJUN16-JUN16-Weekday-03", 
        "trip_id": "ab1893570", 
        "pattern_count": 1633
    }, 
    {
        "block_id": 328300, 
        "direction_id": 1, 
        "hierarchy": 1, 
        "pattern_rank": 2, 
        "pattern_id": 100, 
        "route_id": "88-PrinceGeorge", 
        "direction_code": 0, 
        "trip_headsign": "Westgate Mall", 
        "trip_type": 0, 
        "trip_sequence": 6, 
        "shape_id": "9-88-14", 
        "pattern_code": 100, 
        "service_id": "aaJUN16-JUN16-Weekday-03", 
        "trip_id": "ab1893572", 
        "pattern_count": 1633
    }, 
    {
        "block_id": 328300, 
        "direction_id": 1, 
        "hierarchy": 1, 
        "pattern_rank": 2, 
        "pattern_id": 100, 
        "route_id": "88-PrinceGeorge", 
        "direction_code": 0, 
        "trip_headsign": "Westgate Mall", 
        "trip_type": 0, 
        "trip_sequence": 8, 
        "shape_id": "9-88-14", 
        "pattern_code": 100, 
        "service_id": "aaJUN16-JUN16-Weekday-03", 
        "trip_id": "ab1893574", 
        "pattern_count": 1633
    }, 
    {
        "block_id": 328300, 
        "direction_id": 1, 
        "hierarchy": 1, 
        "pattern_rank": 2, 
        "pattern_id": 100, 
        "route_id": "88-PrinceGeorge", 
        "direction_code": 0, 
        "trip_headsign": "Westgate Mall", 
        "trip_type": 0, 
        "trip_sequence": 10, 
        "shape_id": "9-88-14", 
        "pattern_code": 100, 
        "service_id": "aaJUN16-JUN16-Weekday-03", 
        "trip_id": "ab1893576", 
        "pattern_count": 1633
    }, 
    {
        "block_id": 328300, 
        "direction_id": 1, 
        "hierarchy": 1, 
        "pattern_rank": 2, 
        "pattern_id": 100, 
        "route_id": "88-PrinceGeorge", 
        "direction_code": 0, 
        "trip_headsign": "Westgate Mall", 
        "trip_type": 0, 
        "trip_sequence": 12, 
        "shape_id": "9-88-14", 
        "pattern_code": 100, 
        "service_id": "aaJUN16-JUN16-Weekday-03", 
        "trip_id": "ab1893578", 
        "pattern_count": 1633
    }, 
    {
        "block_id": 328300, 
        "direction_id": 1, 
        "hierarchy": 1, 
        "pattern_rank": 2, 
        "pattern_id": 100, 
        "route_id": "88-PrinceGeorge", 
        "direction_code": 0, 
        "trip_headsign": "Westgate Mall", 
        "trip_type": 0, 
        "trip_sequence": 14, 
        "shape_id": "9-88-14", 
        "pattern_code": 100, 
        "service_id": "aaJUN16-JUN16-Weekday-03", 
        "trip_id": "ab1893580", 
        "pattern_count": 1633
    }, 
    {
        "block_id": 328300, 
        "direction_id": 1, 
        "hierarchy": 1, 
        "pattern_rank": 2, 
        "pattern_id": 100, 
        "route_id": "88-PrinceGeorge", 
        "direction_code": 0, 
        "trip_headsign": "Westgate Mall", 
        "trip_type": 0, 
        "trip_sequence": 16, 
        "shape_id": "9-88-14", 
        "pattern_code": 100, 
        "service_id": "aaJUN16-JUN16-Weekday-03", 
        "trip_id": "ab1893582", 
        "pattern_count": 1633
    }, 
    {
        "block_id": 328300, 
        "direction_id": 1, 
        "hierarchy": 3, 
        "pattern_rank": 19, 
        "pattern_id": 140, 
        "route_id": "88-PrinceGeorge", 
        "direction_code": 0, 
        "trip_headsign": "Westgate Mall", 
        "trip_type": 0, 
        "trip_sequence": 18, 
        "shape_id": "9-88-15", 
        "pattern_code": 140, 
        "service_id": "aaJUN16-JUN16-Weekday-03", 
        "trip_id": "ab1893584", 
        "pattern_count": 58
    }
]